{"_editor_size":"pm","id":"base_projector_medium","modules":[{"type":"DestinationModule","pos":{"x":0.5,"y":1.5,"w":31,"h":3},"align":"left","color":16777215,"arrival":0},{"type":"ArrivalTimeModule","pos":{"x":36.5,"y":1.5,"w":11,"h":3},"align":"right","color":16777215,"arrival":0},{"type":"PlatformNumberModule","pos":{"x":32,"y":1.5,"w":4,"h":3},"align":"center","color":16777215,"arrival":0},{"type":"DestinationModule","pos":{"x":0.5,"y":5.25,"w":31,"h":3},"align":"left","color":16777215,"arrival":1},{"type":"DestinationModule","pos":{"x":0.5,"y":9,"w":31,"h":3},"align":"left","color":16777215,"arrival":2},{"type":"DestinationModule","pos":{"x":0.5,"y":12.75,"w":31,"h":3},"align":"left","color":16777215,"arrival":3},{"type":"DestinationModule","pos":{"x":0.5,"y":16.5,"w":31,"h":3},"align":"left","color":16777215,"arrival":4},{"type":"DestinationModule","pos":{"x":0.5,"y":20.25,"w":31,"h":3},"align":"left","color":16777215,"arrival":5},{"type":"DestinationModule","pos":{"x":0.5,"y":24,"w":31,"h":3},"align":"left","color":16777215,"arrival":6},{"type":"DestinationModule","pos":{"x":0.5,"y":27.75,"w":31,"h":3},"align":"left","color":16777215,"arrival":7},{"type":"PlatformNumberModule","pos":{"x":32,"y":5.25,"w":4,"h":3},"align":"center","color":16777215,"arrival":1},{"type":"PlatformNumberModule","pos":{"x":32,"y":9,"w":4,"h":3},"align":"center","color":16777215,"arrival":2},{"type":"PlatformNumberModule","pos":{"x":32,"y":12.75,"w":4,"h":3},"align":"center","color":16777215,"arrival":3},{"type":"PlatformNumberModule","pos":{"x":32,"y":16.5,"w":4,"h":3},"align":"center","color":16777215,"arrival":4},{"type":"PlatformNumberModule","pos":{"x":32,"y":20.25,"w":4,"h":3},"align":"center","color":16777215,"arrival":5},{"type":"PlatformNumberModule","pos":{"x":32,"y":24,"w":4,"h":3},"align":"center","color":16777215,"arrival":6},{"type":"PlatformNumberModule","pos":{"x":32,"y":27.75,"w":4,"h":3},"align":"center","color":16777215,"arrival":7},{"type":"ArrivalTimeModule","pos":{"x":36.5,"y":5.25,"w":11,"h":3},"align":"right","color":16777215,"arrival":1},{"type":"ArrivalTimeModule","pos":{"x":36.5,"y":9,"w":11,"h":3},"align":"right","color":16777215,"arrival":2},{"type":"ArrivalTimeModule","pos":{"x":36.5,"y":12.75,"w":11,"h":3},"align":"right","color":16777215,"arrival":3},{"type":"ArrivalTimeModule","pos":{"x":36.5,"y":16.5,"w":11,"h":3},"align":"right","color":16777215,"arrival":4},{"type":"ArrivalTimeModule","pos":{"x":36.5,"y":20.25,"w":11,"h":3},"align":"right","color":16777215,"arrival":5},{"type":"ArrivalTimeModule","pos":{"x":36.5,"y":24,"w":11,"h":3},"align":"right","color":16777215,"arrival":6},{"type":"ArrivalTimeModule","pos":{"x":36.5,"y":27.75,"w":11,"h":3},"align":"right","color":16777215,"arrival":7}],"name":"Base Medium Arrival Projector","author":"EpicPuppy613","description":"MTR Built-in layout.\n\nSize: 48 x 32\nArrivals: 8"}